declarativex/__init__.py
declarativex/auth.py
declarativex/client.py
declarativex/compatibility.py
declarativex/dependencies.py
declarativex/exceptions.py
declarativex/executors.py
declarativex/graphql.py
declarativex/methods.py
declarativex/middlewares.py
declarativex/models.py
declarativex/rate_limiter.py
declarativex/retry.py
declarativex/utils.py
declarativex/validation.py
declarativex/warnings.py
declarativex-1.6.6.dist-info/LICENSE
declarativex-1.6.6.dist-info/METADATA
declarativex-1.6.6.dist-info/WHEEL
declarativex-1.6.6.dist-info/RECORD
