Metadata-Version: 2.1
Name: declarativex
Version: 1.6.6
Summary: Declarative HTTP client for Python
Home-page: https://declarativex.dev
License: MIT
Keywords: http,declarative,client,async,httpx,pydantic
Author: Vladyslav Halatskyi
Author-email: xfloydya@gmail.com
Requires-Python: >=3.9,<4
Classifier: Development Status :: 5 - Production/Stable
Classifier: Intended Audience :: Developers
Classifier: Intended Audience :: Information Technology
Classifier: Intended Audience :: System Administrators
Classifier: License :: OSI Approved :: MIT License
Classifier: Operating System :: OS Independent
Classifier: Programming Language :: Python
Classifier: Programming Language :: Python :: 3
Classifier: Programming Language :: Python :: 3.9
Classifier: Programming Language :: Python :: 3.10
Classifier: Programming Language :: Python :: 3.11
Classifier: Programming Language :: Python :: 3.12
Classifier: Programming Language :: Python :: 3 :: Only
Classifier: Programming Language :: Python :: Implementation :: CPython
Classifier: Programming Language :: Python :: Implementation :: PyPy
Classifier: Topic :: Internet :: WWW/HTTP
Classifier: Topic :: Software Development :: Libraries :: Python Modules
Provides-Extra: brotli
Provides-Extra: graphql
Provides-Extra: http2
Requires-Dist: brotli (==v1.6.6) ; extra == "brotli"
Requires-Dist: brotlicffi (==v1.6.6) ; extra == "brotli"
Requires-Dist: graphql-py (==v1.6.6) ; extra == "graphql"
Requires-Dist: h2 (==v1.6.6) ; extra == "http2"
Requires-Dist: httpx (>=0.25.0,<0.26.0)
Requires-Dist: pydantic (>1,<3)
Project-URL: Bug Tracker, https://github.com/floydya/declarativex/issues
Project-URL: Documentation, https://declarativex.dev
Project-URL: Repository, https://github.com/floydya/declarativex
